autoptim/__init__.py
autoptim/autoptim.py
autoptim/test_private.py
autoptim-0.3.dist-info/LICENSE
autoptim-0.3.dist-info/METADATA
autoptim-0.3.dist-info/WHEEL
autoptim-0.3.dist-info/top_level.txt
autoptim-0.3.dist-info/RECORD
