Metadata-Version: 2.1
Name: autoptim
Version: 0.3
Summary: Optimization with autodiff
Home-page: UNKNOWN
Maintainer: Pierre Ablin
Maintainer-email: pierre.ablin@inria.fr
License: MIT
Download-URL: https://github.com/pierreablin/autoptim.git
Platform: any
Classifier: Intended Audience :: Science/Research
Classifier: Intended Audience :: Developers
Classifier: License :: OSI Approved :: MIT License
Classifier: Programming Language :: Python
Classifier: Topic :: Software Development
Classifier: Topic :: Scientific/Engineering
Classifier: Operating System :: Microsoft :: Windows
Classifier: Operating System :: POSIX
Classifier: Operating System :: Unix
Classifier: Operating System :: MacOS
